README.md
setup.py
tail_uwsgi_log/__init__.py
tail_uwsgi_log/config.py
tail_uwsgi_log/monitor.py
tail_uwsgi_log/reader.py
tail_uwsgi_log.egg-info/PKG-INFO
tail_uwsgi_log.egg-info/SOURCES.txt
tail_uwsgi_log.egg-info/dependency_links.txt
tail_uwsgi_log.egg-info/entry_points.txt
tail_uwsgi_log.egg-info/requires.txt
tail_uwsgi_log.egg-info/top_level.txt