Metadata-Version: 2.1
Name: tail-uwsgi-log
Version: 0.0.4
Summary: Tail several uwsgi log files and send an email when error occurs.
Home-page: https://github.com/kant-li/uwsgi_log_analysis
Author: Kant
Author-email: kant@kantli.com
License: MIT License
Keywords: uwsgi log
Platform: UNKNOWN
Classifier: Programming Language :: Python :: 3
Classifier: License :: OSI Approved :: MIT License
Classifier: Operating System :: OS Independent
Requires-Python: >=3.7
